langchain_guardrails/__init__.py
langchain_guardrails/nemo_chain.py
langchain_guardrails-0.0.7.dist-info/METADATA
langchain_guardrails-0.0.7.dist-info/WHEEL
langchain_guardrails-0.0.7.dist-info/licenses/LICENSE
langchain_guardrails-0.0.7.dist-info/RECORD
