Metadata-Version: 2.4
Name: langchain_guardrails
Version: 0.0.7
Summary: Langchain implementation for Guardrails: Nemo
Project-URL: Homepage, https://github.com/skamalj/langchain-guardrails
Project-URL: Documentation, https://github.com/skamalj/langchain-guardrails/blob/main/Readme.md
Project-URL: Repository, https://github.com/skamalj/langchain-guardrails.git
Author-email: Kamal <skamalj@github.com>
License-Expression: MIT AND (Apache-2.0 OR BSD-2-Clause)
License-File: LICENSE
Classifier: License :: OSI Approved :: MIT License
Classifier: Operating System :: OS Independent
Classifier: Programming Language :: Python :: 3
Requires-Python: >=3.10
Requires-Dist: langchain-core>=0.3.45
Requires-Dist: nemoguardrails>=0.11.0
Provides-Extra: dev
Requires-Dist: black; extra == 'dev'
Requires-Dist: isort; extra == 'dev'
Requires-Dist: pytest-cov; extra == 'dev'
Requires-Dist: pytest>=7.0; extra == 'dev'
